wavio.py
wavio-0.0.9.dist-info/METADATA
wavio-0.0.9.dist-info/WHEEL
wavio-0.0.9.dist-info/top_level.txt
wavio-0.0.9.dist-info/RECORD
