Metadata-Version: 2.1
Name: wavio
Version: 0.0.9
Summary: A Python module for reading and writing WAV files using numpy arrays.
Home-page: https://github.com/WarrenWeckesser/wavio
Author: Warren Weckesser
License: BSD
Keywords: wav numpy
Classifier: License :: OSI Approved :: BSD License
Classifier: Intended Audience :: Developers
Classifier: Operating System :: OS Independent
Classifier: Programming Language :: Python :: 3.7
Classifier: Programming Language :: Python :: 3.8
Classifier: Programming Language :: Python :: 3.9
Classifier: Programming Language :: Python :: 3.10
Classifier: Programming Language :: Python :: 3.11
Classifier: Programming Language :: Python :: 3.12
Requires-Dist: numpy>=1.19.0
